opa/__init__.py
opa/client.py
opa/exceptions.py
opa_python-0.0.8.dist-info/LICENSE
opa_python-0.0.8.dist-info/METADATA
opa_python-0.0.8.dist-info/WHEEL
opa_python-0.0.8.dist-info/RECORD
