Metadata-Version: 2.1
Name: opa-python
Version: 0.0.8
Summary: A Python OPA client library
Home-page: https://github.com/heliconhq/opa-python
License: MIT
Author: Gustaf Sjoberg
Author-email: gs@helicon.ai
Requires-Python: >=3.10,<4
Classifier: License :: OSI Approved :: MIT License
Classifier: Operating System :: OS Independent
Classifier: Programming Language :: Python :: 3
Classifier: Programming Language :: Python :: 3.10
Classifier: Programming Language :: Python :: 3.11
Classifier: Programming Language :: Python :: 3.10
Requires-Dist: requests (>=2.28.1,<3.0.0)
Project-URL: Documentation, https://github.com/heliconhq/opa-python
